ClassJsonMapper/Errors.py
ClassJsonMapper/__init__.py
ClassJsonMapper/mapper.py
ClassJsonMapper/parsers.py
ClassJsonMapper-0.1b1.dist-info/LICENSE
ClassJsonMapper-0.1b1.dist-info/METADATA
ClassJsonMapper-0.1b1.dist-info/WHEEL
ClassJsonMapper-0.1b1.dist-info/top_level.txt
ClassJsonMapper-0.1b1.dist-info/RECORD
