Metadata-Version: 2.1
Name: ClassJsonMapper
Version: 0.1b1
Summary: ClassJsonMapper 是一个易于使用的Python库，旨在简化JSON数据与类对象之间的映射和转换过程。通过自定义类方法，它使得处理JSON文件变得直观、安全且高效。
Home-page: https://github.com/PYmili/ClassJsonMapper
Author: PYmili
Author-email: mc2005wj@163.com
License: MIT
Keywords: json,mapping,data serialization,object mapping
Classifier: Development Status :: 4 - Beta
Classifier: Intended Audience :: Developers
Classifier: Topic :: Software Development :: Libraries :: Python Modules
Classifier: License :: OSI Approved :: MIT License
Classifier: Programming Language :: Python :: 3.8
Classifier: Programming Language :: Python :: 3.9
Classifier: Programming Language :: Python :: 3.10
Classifier: Programming Language :: Python :: 3.11
Classifier: Programming Language :: Python :: 3.12
License-File: LICENSE
